django_visit_on_site_in_new_window/__init__.py
django_visit_on_site_in_new_window/admin.py
django_visit_on_site_in_new_window/apps.py
django_visit_on_site_in_new_window/models.py
django_visit_on_site_in_new_window/tests.py
django_visit_on_site_in_new_window/views.py
django_visit_on_site_in_new_window/migrations/__init__.py
django_visit_on_site_in_new_window/static/django-visit-on-site-in-new-window/js/django-visit-on-site-in-new-window.js
django_visit_on_site_in_new_window-0.1.2.dist-info/licenses/LICENSE
django_visit_on_site_in_new_window-0.1.2.dist-info/METADATA
django_visit_on_site_in_new_window-0.1.2.dist-info/WHEEL
django_visit_on_site_in_new_window-0.1.2.dist-info/top_level.txt
django_visit_on_site_in_new_window-0.1.2.dist-info/RECORD
