Metadata-Version: 2.4
Name: django-visit-on-site-in-new-window
Version: 0.1.2
Summary: Turn VISIT-ON-SITE button to open in the new window on Django's admin site.
Author: rRR0VrFP
Maintainer: rRR0VrFP
License: MIT
Keywords: django admin extentions,django visit on site in new window
Classifier: Development Status :: 5 - Production/Stable
Classifier: Intended Audience :: Developers
Classifier: Topic :: Software Development :: Libraries :: Python Modules
Classifier: License :: OSI Approved :: MIT License
Classifier: Programming Language :: Python :: 3
Classifier: Programming Language :: Python :: 3 :: Only
License-File: LICENSE
Requires-Dist: django
Requires-Dist: django-static-jquery3>=3.3.1.1
Dynamic: author
Dynamic: classifier
Dynamic: description
Dynamic: description-content-type
Dynamic: keywords
Dynamic: license
Dynamic: license-file
Dynamic: maintainer
Dynamic: requires-dist
Dynamic: summary
